{
    "tags": [
        {
            "name": "hexID",
            "value": "PRA4201"
        },
        {
            "name": "oompType",
            "value": "PROJ"
        },
        {
            "name": "oompSize",
            "value": "ADAF"
        },
        {
            "name": "oompColor",
            "value": "4201"
        },
        {
            "name": "oompDesc",
            "value": "STAN"
        },
        {
            "name": "oompIndex",
            "value": "01"
        },
        {
            "name": "oompName",
            "value": "Adafruit AirLift Breakout PCB"
        },
        {
            "name": "sources",
            "value": "All source files from https://github.com/adafruit/Adafruit-AirLift-Breakout-PCB (source licence details in srcLicense.md)"
        },
        {
            "name": "linkBuyPage",
            "value": "http://www.adafruit.com/products/4201"
        },
        {
            "name": "oompPart",
            "value": "CAPE-0805-X-UNMATCHED-01, C1, 3.0479999999999996, 24.764999999999997, 180"
        },
        {
            "name": "oompPart",
            "value": "CAPE-0805-X-UNMATCHED-01, C2, 3.0479999999999996, 15.366999999999999, 0"
        },
        {
            "name": "oompPart",
            "value": "CAPE-0805-X-UNMATCHED-01, C3, 3.0479999999999996, 20.955, 180"
        },
        {
            "name": "oompPart",
            "value": "CAPE-0805-X-UNMATCHED-01, C4, 3.0479999999999996, 22.86, 180"
        },
        {
            "name": "oompPart",
            "value": "CAPE-0603-X-NF100-01, C5, 30.733999999999998, 24.002999999999997, 270"
        },
        {
            "name": "oompPart",
            "value": "UNMATCHED-UNMATCHED-X-UNMATCHED-01, D1, 5.08, 13.589, 90"
        },
        {
            "name": "oompPart",
            "value": "UNMATCHED-UNMATCHED-X-UNMATCHED-01, D2, 5.08, 10.921999999999999, 90"
        },
        {
            "name": "oompPart",
            "value": "UNMATCHED-UNMATCHED-X-UNMATCHED-01, D3, 5.08, 12.318999999999999, 90"
        },
        {
            "name": "oompPart",
            "value": "SKIP-UNMATCHED-X-UNMATCHED-01, FID1, 0.7619999999999999, 7.238999999999999, 0"
        },
        {
            "name": "oompPart",
            "value": "SKIP-UNMATCHED-X-UNMATCHED-01, FID3, 30.479999999999997, 27.051, 0"
        },
        {
            "name": "oompPart",
            "value": "UNMATCHED-UNMATCHED-X-UNMATCHED-01, IC1, 27.813, 23.749, 270"
        },
        {
            "name": "oompPart",
            "value": "UNMATCHED-UNMATCHED-X-UNMATCHED-01, JP1, 15.875, 2.54, 0"
        },
        {
            "name": "oompPart",
            "value": "UNMATCHED-UNMATCHED-X-UNMATCHED-01, Q3, 27.304999999999996, 7.365999999999999, 180"
        },
        {
            "name": "oompPart",
            "value": "RESE-UNMATCHED-X-O103-01, R2, 27.686, 10.795, 0"
        },
        {
            "name": "oompPart",
            "value": "RESE-UNMATCHED-X-UNMATCHED-01, R6, 2.2859999999999996, 12.318999999999999, 270"
        },
        {
            "name": "oompPart",
            "value": "SKIP-UNMATCHED-X-UNMATCHED-01, U$15, 2.54, 30.353, 0"
        },
        {
            "name": "oompPart",
            "value": "SKIP-UNMATCHED-X-UNMATCHED-01, U$16, 28.701999999999995, 29.845, 0"
        },
        {
            "name": "oompPart",
            "value": "UNMATCHED-UNMATCHED-X-UNMATCHED-01, U1, 3.0479999999999996, 18.034, 270"
        },
        {
            "name": "oompPart",
            "value": "UNMATCHED-UNMATCHED-X-UNMATCHED-01, U2, 28.448, 17.145, 0"
        },
        {
            "name": "oompPart",
            "value": "UNMATCHED-UNMATCHED-X-UNMATCHED-01, X1, 15.875, 20.32, 0"
        },
        {
            "name": "rawPart",
            "value": "C1, 10uF, 0805-NO, microbuilder, (0.12, 0.975), R180"
        },
        {
            "name": "rawPart",
            "value": "C2, 10uF, 0805-NO, microbuilder, (0.12, 0.605), R0"
        },
        {
            "name": "rawPart",
            "value": "C3, 10uF, 0805-NO, microbuilder, (0.12, 0.825), R180"
        },
        {
            "name": "rawPart",
            "value": "C4, 10uF, 0805-NO, microbuilder, (0.12, 0.9), R180"
        },
        {
            "name": "rawPart",
            "value": "C5, 0.1uF, 0603-NO, microbuilder, (1.21, 0.945), R270"
        },
        {
            "name": "rawPart",
            "value": "D1, GREEN, CHIPLED_0603_NOOUTLINE, microbuilder, (0.2, 0.535), R90"
        },
        {
            "name": "rawPart",
            "value": "D2, BLUE, CHIPLED_0603_NOOUTLINE, microbuilder, (0.2, 0.43), R90"
        },
        {
            "name": "rawPart",
            "value": "D3, RED, CHIPLED_0603_NOOUTLINE, microbuilder, (0.2, 0.485), R90"
        },
        {
            "name": "rawPart",
            "value": "FID1, FIDUCIAL_1MM, FIDUCIAL_1MM, microbuilder, (0.03, 0.285), R0"
        },
        {
            "name": "rawPart",
            "value": "FID3, FIDUCIAL_1MM, FIDUCIAL_1MM, microbuilder, (1.2, 1.065), R0"
        },
        {
            "name": "rawPart",
            "value": "IC1, 74AHC1G125, SOT23-5L, adafruit, (1.095, 0.935), R270"
        },
        {
            "name": "rawPart",
            "value": "JP1, 1X12_ROUND, microbuilder, (0.625, 0.1), R0"
        },
        {
            "name": "rawPart",
            "value": "Q3, BSS138, SOT23-WIDE, microbuilder, (1.075, 0.29), R180"
        },
        {
            "name": "rawPart",
            "value": "R2, 10K, RESPACK_4X0603, microbuilder, (1.09, 0.425), R0"
        },
        {
            "name": "rawPart",
            "value": "R6, 1K, RESPACK_4X0603, microbuilder, (0.09, 0.485), R270"
        },
        {
            "name": "rawPart",
            "value": "U$15, MOUNTINGHOLE2.5, MOUNTINGHOLE_2.5_PLATED, microbuilder, (0.1, 1.195), R0"
        },
        {
            "name": "rawPart",
            "value": "U$16, MOUNTINGHOLE2.5, MOUNTINGHOLE_2.5_PLATED, microbuilder, (1.13, 1.175), R0"
        },
        {
            "name": "rawPart",
            "value": "U1, AP2112-3.3, SOT23-5, microbuilder, (0.12, 0.71), R270"
        },
        {
            "name": "rawPart",
            "value": "U2, 74AHC4050, TSSOP16, microbuilder, (1.12, 0.675), R0"
        },
        {
            "name": "rawPart",
            "value": "X1, ESP32_WROOM32, WROOM32, microbuilder, (0.625, 0.8), R0"
        },
        {
            "name": "oompID",
            "value": "PROJ-ADAF-4201-STAN-01"
        },
        {
            "name": "name",
            "value": "Adafruit"
        }
    ]
}