{
    "tags": [
        {
            "name": "hexID",
            "value": "PRS15316"
        },
        {
            "name": "oompType",
            "value": "PROJ"
        },
        {
            "name": "oompSize",
            "value": "SPAR"
        },
        {
            "name": "oompColor",
            "value": "15316"
        },
        {
            "name": "oompDesc",
            "value": "STAN"
        },
        {
            "name": "oompIndex",
            "value": "01"
        },
        {
            "name": "oompName",
            "value": "Pi Servo Hat"
        },
        {
            "name": "sources",
            "value": "All source files from https://github.com/sparkfun/Pi_Servo_Hat (source licence details in srcLicense.md)"
        },
        {
            "name": "linkBuyPage",
            "value": "https://github.com/sparkfun/15316"
        },
        {
            "name": "oompID",
            "value": "PROJ-SPAR-15316-STAN-01"
        },
        {
            "name": "name",
            "value": "Sparkfun"
        }
    ]
}