{
    "tags": [
        {
            "name": "hexID",
            "value": "PRS10901"
        },
        {
            "name": "oompType",
            "value": "PROJ"
        },
        {
            "name": "oompSize",
            "value": "SPAR"
        },
        {
            "name": "oompColor",
            "value": "10901"
        },
        {
            "name": "oompDesc",
            "value": "STAN"
        },
        {
            "name": "oompIndex",
            "value": "01"
        },
        {
            "name": "oompName",
            "value": "Infrared Proximity Breakout-VCNL4000"
        },
        {
            "name": "sources",
            "value": "All source files from https://github.com/sparkfun/Infrared_Proximity_Breakout-VCNL4000 (source licence details in srcLicense.md)"
        },
        {
            "name": "linkBuyPage",
            "value": "https://www.sparkfun.com/products/10901"
        },
        {
            "name": "oompID",
            "value": "PROJ-SPAR-10901-STAN-01"
        },
        {
            "name": "oompParts",
            "value": "C1,UNMATCHED-UNMATCHED-UNMATCHED-UNMATCHED-UNMATCHED"
        },
        {
            "name": "oompParts",
            "value": "C2,UNMATCHED-UNMATCHED-UNMATCHED-UNMATCHED-UNMATCHED"
        },
        {
            "name": "oompParts",
            "value": "C3,UNMATCHED-UNMATCHED-UNMATCHED-UNMATCHED-UNMATCHED"
        },
        {
            "name": "oompParts",
            "value": "JP1,UNMATCHED-UNMATCHED-UNMATCHED-UNMATCHED-UNMATCHED"
        },
        {
            "name": "oompParts",
            "value": "JP2,UNMATCHED-UNMATCHED-UNMATCHED-UNMATCHED-UNMATCHED"
        },
        {
            "name": "oompParts",
            "value": "JP3,UNMATCHED-UNMATCHED-UNMATCHED-UNMATCHED-UNMATCHED"
        },
        {
            "name": "oompParts",
            "value": "JP4,UNMATCHED-UNMATCHED-UNMATCHED-UNMATCHED-UNMATCHED"
        },
        {
            "name": "oompParts",
            "value": "JP5,UNMATCHED-UNMATCHED-UNMATCHED-UNMATCHED-UNMATCHED"
        },
        {
            "name": "oompParts",
            "value": "U$1,UNMATCHED-UNMATCHED-UNMATCHED-UNMATCHED-UNMATCHED"
        },
        {
            "name": "oompParts",
            "value": "U$2,UNMATCHED-UNMATCHED-UNMATCHED-UNMATCHED-UNMATCHED"
        },
        {
            "name": "oompParts",
            "value": "U1,UNMATCHED-UNMATCHED-UNMATCHED-UNMATCHED-UNMATCHED"
        },
        {
            "name": "rawParts",
            "value": "C1,0.1uF,CAP0402-CAP,0402-CAP,Capacitor,,"
        },
        {
            "name": "rawParts",
            "value": "C2,0.1uF,CAP0402-CAP,0402-CAP,Capacitor,,"
        },
        {
            "name": "rawParts",
            "value": "C3,10uF,CAP_POL1206,EIA3216,Capacitor Polarized,,"
        },
        {
            "name": "rawParts",
            "value": "JP1,,M05PTH,1X05,Header 5,,"
        },
        {
            "name": "rawParts",
            "value": "JP2,LOGO-SFENW2,LOGO-SFENW2,SFE-NEW-WEB,Spark Fun Electronics PCB Logo,,"
        },
        {
            "name": "rawParts",
            "value": "JP3,STAND-OFF,STAND-OFF,STAND-OFF,Stand Off,,"
        },
        {
            "name": "rawParts",
            "value": "JP4,STAND-OFF,STAND-OFF,STAND-OFF,Stand Off,,"
        },
        {
            "name": "rawParts",
            "value": "JP5,LOGO-SFESK,LOGO-SFESK,SFE-LOGO-FLAME,Spark Fun Electronics PCB Logo,,"
        },
        {
            "name": "rawParts",
            "value": "JP6,FIDUCIALUFIDUCIAL,FIDUCIALUFIDUCIAL,MICRO-FIDUCIAL,Fiducial Alignment Points,,"
        },
        {
            "name": "rawParts",
            "value": "JP7,FIDUCIALUFIDUCIAL,FIDUCIALUFIDUCIAL,MICRO-FIDUCIAL,Fiducial Alignment Points,,"
        },
        {
            "name": "rawParts",
            "value": "U$1,OSHW-LOGOS,OSHW-LOGOS,OSHW-LOGO-S,Open Source Hardware Logo This logo indicates the piece of hardware it is found on incorporates a OSHW license and/or adheres to the definition of open source hardware found here: http://freedomdefined.org/OSHW,,"
        },
        {
            "name": "rawParts",
            "value": "U$2,CREATIVE_COMMONS,CREATIVE_COMMONS,CREATIVE_COMMONS,,,"
        },
        {
            "name": "rawParts",
            "value": "U1,VCNL4000,VCNL4000,VCNL4000,VNCL4000,,"
        },
        {
            "name": "oompID",
            "value": "PROJ-SPAR-10901-STAN-01"
        },
        {
            "name": "name",
            "value": "Sparkfun"
        }
    ]
}