{
    "tags": [
        {
            "name": "hexID",
            "value": "PRS13688"
        },
        {
            "name": "oompType",
            "value": "PROJ"
        },
        {
            "name": "oompSize",
            "value": "SPAR"
        },
        {
            "name": "oompColor",
            "value": "13688"
        },
        {
            "name": "oompDesc",
            "value": "STAN"
        },
        {
            "name": "oompIndex",
            "value": "01"
        },
        {
            "name": "oompName",
            "value": "MyoWare LED Shield"
        },
        {
            "name": "sources",
            "value": "All source files from https://github.com/sparkfun/MyoWare_LED_Shield (source licence details in srcLicense.md)"
        },
        {
            "name": "linkBuyPage",
            "value": "https://www.sparkfun.com/products/13688"
        },
        {
            "name": "oompPart",
            "value": "CAPE-0603-X-UNMATCHED-01, C1, 43.561, 20.1295, M180"
        },
        {
            "name": "oompPart",
            "value": "CAPE-0603-X-UNMATCHED-01, C2, 35.2425, 17.525999999999996, M270"
        },
        {
            "name": "oompPart",
            "value": "UNMATCHED-0603-X-UNMATCHED-01, D1, 48.5775, 17.779999999999998, M90"
        },
        {
            "name": "oompPart",
            "value": "UNMATCHED-0603-X-UNMATCHED-01, D2, 48.5775, 15.938499999999998, M90"
        },
        {
            "name": "oompPart",
            "value": "UNMATCHED-UNMATCHED-X-UNMATCHED-01, D3, 36.512499999999996, 10.921999999999999, 180"
        },
        {
            "name": "oompPart",
            "value": "UNMATCHED-UNMATCHED-X-UNMATCHED-01, D4, 15.8115, 10.921999999999999, 180"
        },
        {
            "name": "oompPart",
            "value": "SKIP-UNMATCHED-X-UNMATCHED-01, FID1, 5.7912, 20.5486, M0"
        },
        {
            "name": "oompPart",
            "value": "SKIP-UNMATCHED-X-UNMATCHED-01, FID2, 46.2534, 1.27, M0"
        },
        {
            "name": "oompPart",
            "value": "SKIP-UNMATCHED-X-UNMATCHED-01, FID3, 46.2534, 1.27, 0"
        },
        {
            "name": "oompPart",
            "value": "SKIP-UNMATCHED-X-UNMATCHED-01, FID4, 5.7912, 20.5486, 0"
        },
        {
            "name": "oompPart",
            "value": "UNMATCHED-UNMATCHED-X-UNMATCHED-01, JP1, 1.5239999999999998, 13.462, 270"
        },
        {
            "name": "oompPart",
            "value": "UNMATCHED-UNMATCHED-X-UNMATCHED-01, JP2, 50.4825, 13.462, 270"
        },
        {
            "name": "oompPart",
            "value": "UNMATCHED-UNMATCHED-X-UNMATCHED-01, JP3, 49.466499999999996, 5.0165, 225"
        },
        {
            "name": "oompPart",
            "value": "UNMATCHED-UNMATCHED-X-UNMATCHED-01, JP4, 26.12700007, 19.8755, M270"
        },
        {
            "name": "oompPart",
            "value": "UNMATCHED-UNMATCHED-X-UNMATCHED-01, MODE, 5.225596864, 5.5322030579999995, M315"
        },
        {
            "name": "oompPart",
            "value": "RESE-0603-X-UNMATCHED-01, R1, 12.6365, 2.3495, M90"
        },
        {
            "name": "oompPart",
            "value": "RESE-0603-X-UNMATCHED-01, R2, 14.731999999999998, 2.3495, M270"
        },
        {
            "name": "oompPart",
            "value": "RESE-0603-X-O331-01, R3, 43.561, 18.160999999999998, M0"
        },
        {
            "name": "oompPart",
            "value": "RESE-0603-X-O103-01, R4, 43.561, 16.256, M0"
        },
        {
            "name": "oompPart",
            "value": "RESE-0603-X-O331-01, R5, 43.561, 14.350999999999997, M180"
        },
        {
            "name": "oompPart",
            "value": "UNMATCHED-UNMATCHED-X-UNMATCHED-01, U1, 38.989, 17.7165, M90"
        },
        {
            "name": "oompPart",
            "value": "UNMATCHED-UNMATCHED-X-UNMATCHED-01, U2, 10.6045, 10.921999999999999, M45"
        },
        {
            "name": "rawPart",
            "value": "C1, 4.7uF, 0603-CAP, SparkFun-Capacitors, (1.715, 0.7925), MR180"
        },
        {
            "name": "rawPart",
            "value": "C2, 4.7uF, 0603-CAP, SparkFun-Capacitors, (1.3875, 0.69), MR270"
        },
        {
            "name": "rawPart",
            "value": "D1, RED, LED-0603, SparkFun-LED, (1.9125, 0.7), MR90"
        },
        {
            "name": "rawPart",
            "value": "D2, GREEN, LED-0603, SparkFun-LED, (1.9125, 0.6275), MR90"
        },
        {
            "name": "rawPart",
            "value": "D3, SMA-B500, LED_BAR_SMD, Testing, (1.4375, 0.43), R180"
        },
        {
            "name": "rawPart",
            "value": "D4, SMA-B500, LED_BAR_SMD, Testing, (0.6225, 0.43), R180"
        },
        {
            "name": "rawPart",
            "value": "FID1, FIDUCIAL1X2, FIDUCIAL-1X2, SparkFun-Aesthetics, (0.228, 0.809), MR0"
        },
        {
            "name": "rawPart",
            "value": "FID2, FIDUCIAL1X2, FIDUCIAL-1X2, SparkFun-Aesthetics, (1.821, 0.05), MR0"
        },
        {
            "name": "rawPart",
            "value": "FID3, FIDUCIAL1X2, FIDUCIAL-1X2, SparkFun-Aesthetics, (1.821, 0.05), R0"
        },
        {
            "name": "rawPart",
            "value": "FID4, FIDUCIAL1X2, FIDUCIAL-1X2, SparkFun-Aesthetics, (0.228, 0.809), R0"
        },
        {
            "name": "rawPart",
            "value": "JP1, Power, 1X03_NO_SILK, SparkFun-Connectors, (0.06, 0.53), R270"
        },
        {
            "name": "rawPart",
            "value": "JP2, Signal, 1X03_NO_SILK, SparkFun-Connectors, (1.9875, 0.53), R270"
        },
        {
            "name": "rawPart",
            "value": "JP3, LiPo, 1X02_NO_SILK, SparkFun-Connectors, (1.9475, 0.1975), R225"
        },
        {
            "name": "rawPart",
            "value": "JP4, USB-B-MICRO-SMD_V03, SparkFun-Connectors, (1.02862205, 0.7825), MR270"
        },
        {
            "name": "rawPart",
            "value": "MODE, JUMPER-PAD-2-NC_BY_TRACE, PAD-JUMPER-2-NC_BY_TRACE_YES_SILK, SparkFun-Passives, (0.20573216, 0.21780327), MR315"
        },
        {
            "name": "rawPart",
            "value": "R1, 6.49k, R0603, resistor, (0.4975, 0.0925), MR90"
        },
        {
            "name": "rawPart",
            "value": "R2, 7.5k, R0603, resistor, (0.58, 0.0925), MR270"
        },
        {
            "name": "rawPart",
            "value": "R3, 330, 0603-RES, SparkFun-Resistors, (1.715, 0.715), MR0"
        },
        {
            "name": "rawPart",
            "value": "R4, 10K, 0603-RES, SparkFun-Resistors, (1.715, 0.64), MR0"
        },
        {
            "name": "rawPart",
            "value": "R5, 330, 0603-RES, SparkFun-Resistors, (1.715, 0.565), MR180"
        },
        {
            "name": "rawPart",
            "value": "U1, MCP73831, SOT23-5, SparkFun-PowerIC, (1.535, 0.6975), MR90"
        },
        {
            "name": "rawPart",
            "value": "U2, LM3914V, PLCC20S, Testing, (0.4175, 0.43), MR45"
        },
        {
            "name": "oompID",
            "value": "PROJ-SPAR-13688-STAN-01"
        },
        {
            "name": "name",
            "value": "Sparkfun"
        }
    ]
}