{
    "tags": [
        {
            "name": "hexID",
            "value": "PRS15247"
        },
        {
            "name": "oompType",
            "value": "PROJ"
        },
        {
            "name": "oompSize",
            "value": "SPAR"
        },
        {
            "name": "oompColor",
            "value": "15247"
        },
        {
            "name": "oompDesc",
            "value": "STAN"
        },
        {
            "name": "oompIndex",
            "value": "01"
        },
        {
            "name": "oompName",
            "value": "GNSS Chip Antenna Evaluation Board"
        },
        {
            "name": "sources",
            "value": "All source files from https://github.com/sparkfun/GNSS_Chip_Antenna_Evaluation_Board (source licence details in srcLicense.md)"
        },
        {
            "name": "linkBuyPage",
            "value": "https://www.sparkfun.com/products/15247"
        },
        {
            "name": "oompPart",
            "value": "UNMATCHED-UNMATCHED-X-UNMATCHED-01, J1, 34.29, 32.004, 90"
        },
        {
            "name": "oompPart",
            "value": "UNMATCHED-UNMATCHED-X-UNMATCHED-01, J2, 14.477999999999998, 2.667, 90"
        },
        {
            "name": "oompPart",
            "value": "UNMATCHED-UNMATCHED-X-UNMATCHED-01, J3, 27.94, 9.779, 0"
        },
        {
            "name": "oompPart",
            "value": "UNMATCHED-UNMATCHED-X-UNMATCHED-01, J4, 57.715999884, 3.8099999999999996, 270"
        },
        {
            "name": "oompPart",
            "value": "UNMATCHED-UNMATCHED-X-UNMATCHED-01, J5, 2.1590000000000003, 27.686, 90"
        },
        {
            "name": "oompPart",
            "value": "UNMATCHED-UNMATCHED-X-UNMATCHED-01, J6, 53.339999999999996, 25.4, 0"
        },
        {
            "name": "oompPart",
            "value": "UNMATCHED-UNMATCHED-X-UNMATCHED-01, JP8, 49.022, 34.798, 0"
        },
        {
            "name": "oompPart",
            "value": "UNMATCHED-UNMATCHED-X-UNMATCHED-01, JP9, 0.7619999999999999, 0.7619999999999999, 0"
        },
        {
            "name": "oompPart",
            "value": "RESE-0402-X-UNMATCHED-01, R1, 56.007, 1.651, 180"
        },
        {
            "name": "oompPart",
            "value": "UNMATCHED-UNMATCHED-X-UNMATCHED-01, Y2, 12.7, 13.97, 0"
        },
        {
            "name": "oompPart",
            "value": "UNMATCHED-UNMATCHED-X-UNMATCHED-01, Y3, 36.83, 6.35, 180"
        },
        {
            "name": "oompPart",
            "value": "UNMATCHED-UNMATCHED-X-UNMATCHED-01, Y4, 52.06999999999999, 1.1429999999999998, 0"
        },
        {
            "name": "oompPart",
            "value": "UNMATCHED-UNMATCHED-X-UNMATCHED-01, Y5, 4.064, 33.019999999999996, 270"
        },
        {
            "name": "oompPart",
            "value": "UNMATCHED-UNMATCHED-X-UNMATCHED-01, Y6, 58.419999999999995, 30.353, 270"
        },
        {
            "name": "oompPart",
            "value": "UNMATCHED-UNMATCHED-X-UNMATCHED-01, Y7, 40.64, 34.29, 180"
        },
        {
            "name": "rawPart",
            "value": "J1, U.FL, U.FL, SparkFun-Connectors, (1.35, 1.26), R90"
        },
        {
            "name": "rawPart",
            "value": "J2, U.FL, U.FL, SparkFun-Connectors, (0.57, 0.105), R90"
        },
        {
            "name": "rawPart",
            "value": "J3, U.FL, U.FL, SparkFun-Connectors, (1.1, 0.385), R0"
        },
        {
            "name": "rawPart",
            "value": "J4, U.FL, U.FL, SparkFun-Connectors, (2.27228346, 0.15), R270"
        },
        {
            "name": "rawPart",
            "value": "J5, U.FL, U.FL, SparkFun-Connectors, (0.085, 1.09), R90"
        },
        {
            "name": "rawPart",
            "value": "J6, U.FL, U.FL, SparkFun-Connectors, (2.1, 1), R0"
        },
        {
            "name": "rawPart",
            "value": "JP8, FIDUCIAL1X2, FIDUCIAL-1X2, SparkFun, (1.93, 1.37), R0"
        },
        {
            "name": "rawPart",
            "value": "JP9, FIDUCIAL1X2, FIDUCIAL-1X2, SparkFun, (0.03, 0.03), R0"
        },
        {
            "name": "rawPart",
            "value": "R1, 0, 0402, SparkFun-Resistors, (2.205, 0.065), R180"
        },
        {
            "name": "rawPart",
            "value": "Y2, PUCK, TE_PUCK, SparkFun-GPS, (0.5, 0.55), R0"
        },
        {
            "name": "rawPart",
            "value": "Y3, CUBE, MOLEX_GNSS_CUBE, SparkFun-GPS, (1.45, 0.25), R180"
        },
        {
            "name": "rawPart",
            "value": "Y4, CHIP, MOLEX_GNSS_CHIP, SparkFun-GPS, (2.05, 0.045), R0"
        },
        {
            "name": "rawPart",
            "value": "Y5, MOLDED, MLOEX_GNSS_MOLDED, SparkFun-GPS, (0.16, 1.3), R270"
        },
        {
            "name": "rawPart",
            "value": "Y6, W3062A, W3062A, SparkFun-GPS, (2.3, 1.195), R270"
        },
        {
            "name": "rawPart",
            "value": "Y7, W3011, W3011, SparkFun-GPS, (1.6, 1.35), R180"
        },
        {
            "name": "oompID",
            "value": "PROJ-SPAR-15247-STAN-01"
        },
        {
            "name": "name",
            "value": "Sparkfun"
        }
    ]
}