{
    "tags": [
        {
            "name": "hexID",
            "value": "PRS15272"
        },
        {
            "name": "oompType",
            "value": "PROJ"
        },
        {
            "name": "oompSize",
            "value": "SPAR"
        },
        {
            "name": "oompColor",
            "value": "15272"
        },
        {
            "name": "oompDesc",
            "value": "STAN"
        },
        {
            "name": "oompIndex",
            "value": "01"
        },
        {
            "name": "oompName",
            "value": "gator soil"
        },
        {
            "name": "sources",
            "value": "All source files from https://github.com/sparkfun/gator_soil (source licence details in srcLicense.md)"
        },
        {
            "name": "linkBuyPage",
            "value": "https://github.com/sparkfun/15272"
        },
        {
            "name": "oompID",
            "value": "PROJ-SPAR-15272-STAN-01"
        },
        {
            "name": "name",
            "value": "Sparkfun"
        }
    ]
}