{
    "tags": [
        {
            "name": "hexID",
            "value": "PRS8480"
        },
        {
            "name": "oompType",
            "value": "PROJ"
        },
        {
            "name": "oompSize",
            "value": "SPAR"
        },
        {
            "name": "oompColor",
            "value": "8480"
        },
        {
            "name": "oompDesc",
            "value": "STAN"
        },
        {
            "name": "oompIndex",
            "value": "01"
        },
        {
            "name": "oompName",
            "value": "Gainer PSoC Development Board"
        },
        {
            "name": "sources",
            "value": "All source files from https://github.com/sparkfun/Gainer_PSoC_Development_Board (source licence details in srcLicense.md)"
        },
        {
            "name": "linkBuyPage",
            "value": "https://www.sparkfun.com/products/8480"
        },
        {
            "name": "oompID",
            "value": "PROJ-SPAR-8480-STAN-01"
        },
        {
            "name": "oompID",
            "value": "PROJ-SPAR-8480-STAN-01"
        },
        {
            "name": "name",
            "value": "Sparkfun"
        }
    ]
}